selenite/__init__.py
selenite/managed.py
selenite/common/__init__.py
selenite/common/helpers.py
selenite/common/random_utils.py
selenite/common/time_method.py
selenite/core/__init__.py
selenite/core/configuration.py
selenite/core/entity.py
selenite/core/http_request.py
selenite/core/locator.py
selenite/core/page_factory.py
selenite/support/__init__.py
selenite/support/by.py
selenite-3.0.dist-info/LICENSE
selenite-3.0.dist-info/METADATA
selenite-3.0.dist-info/WHEEL
selenite-3.0.dist-info/top_level.txt
selenite-3.0.dist-info/RECORD
